winpwn/__init__.py
winpwn/asm.py
winpwn/context.py
winpwn/dbg.py
winpwn/misc.py
winpwn/win.py
winpwn/wincs.py
winpwn/winfile.py
winpwn/winpwn.py
winpwn-0.3.0.dist-info/METADATA
winpwn-0.3.0.dist-info/WHEEL
winpwn-0.3.0.dist-info/top_level.txt
winpwn-0.3.0.dist-info/RECORD
